goyabucli/__init__.py
goyabucli/__main__.py
goyabucli/anilistManager.py
goyabucli/cli.py
goyabucli/dropdown.py
goyabucli/playerManager.py
goyabucli/progress.py
goyabucli/rawserver.py
goyabucli/scraper.py
goyabucli/scraperManager.py
goyabucli/serverManager.py
goyabucli/sessionManager.py
goyabucli/translation.py
goyabucli/utils.py
goyabucli/extractors/__init__.py
goyabucli/extractors/blogger.py
goyabucli/scrapers/__init__.py
goyabucli/scrapers/animefire.py
goyabucli/scrapers/gogoanime.py
goyabucli/scrapers/goyabu.py
goyabucli/scrapers/superanimes.py
goyabucli/scrapers/vizer.py
goyabu_cli-1.0.15.dist-info/LICENSE
goyabu_cli-1.0.15.dist-info/METADATA
goyabu_cli-1.0.15.dist-info/WHEEL
goyabu_cli-1.0.15.dist-info/entry_points.txt
goyabu_cli-1.0.15.dist-info/top_level.txt
goyabu_cli-1.0.15.dist-info/RECORD
