Metadata-Version: 2.1
Name: goyabu-cli
Version: 1.0.15
Summary: quickly play anime from terminal
Home-page: https://github.com/AlanJs26/goyabu-cli
Author: AlanJS26
Author-email: AlanJS26 <alanjoses.29@gmail.com>
License: MIT License
Project-URL: Homepage, https://github.com/AlanJs26/goyabu-cli
Keywords: python,cli,anime
Requires-Python: >=3.6
License-File: LICENSE
Requires-Dist: parsel (==1.7.0)
Requires-Dist: PyBypass (==2.0.1)
Requires-Dist: python-mpv-jsonipc (==1.1.13)
Requires-Dist: requests (==2.28.1)
Requires-Dist: rich (==13.3.1)
Requires-Dist: setuptools (==64.0.1)
Requires-Dist: termtables (==0.2.4)
